{"be_authentication_2fa_index.md":"D2z-AEaH","be_authentication_jwt_index.md":"CwrIvajr","be_authentication_oauth2_1.weixin.md":"nnlZUivp","be_authentication_oauth2_2.github.md":"DX9WIds3","be_authentication_oauth2_index.md":"duaOEkTI","be_eggjs_docs_index.md":"CnNAQBO4","be_go_docs_1.setup.md":"DwesQ7zj","be_go_docs_10.networking.md":"Dy-Hs48s","be_go_docs_11.database.md":"vCpILZ2q","be_go_docs_12.web-development.md":"C2NTenPn","be_go_docs_13.testing.md":"7hvzymVH","be_go_docs_14.performance.md":"DlldWYvp","be_go_docs_15.security.md":"K7BGtLd5","be_go_docs_2.syntax.md":"D7Gs-hvS","be_go_docs_3.composite-types.md":"BcqulfPd","be_go_docs_4.functions.md":"BUB8niku","be_go_docs_5.concurrency.md":"DnhbSF9v","be_go_docs_6.standard-library.md":"DW2SActR","be_go_docs_7.compilation.md":"Cu4DkGmJ","be_go_docs_8.error-handling.md":"u1WrtqBa","be_go_docs_9.file-io.md":"ByNrwmEF","be_go_docs_index.md":"D4p4xnJT","be_java_docs_1.setup.md":"DBkMhKeh","be_java_docs_10.bundle.md":"CSFL6Bc8","be_java_docs_11.webapp.md":"BwBZrGHH","be_java_docs_12.module.md":"COBGlo5S","be_java_docs_13.io.md":"BNthb9Cn","be_java_docs_14.database.md":"OMxSXARw","be_java_docs_15.open-library.md":"PKjVQEqj","be_java_docs_2.datatype.md":"B40Xousm","be_java_docs_3.syntax.md":"CKS9hPgb","be_java_docs_4.array.md":"tF2Xs2Fu","be_java_docs_5.functions.md":"DSdha-Hl","be_java_docs_6.oop.md":"D3qDplKg","be_java_docs_7.reflection.md":"OjyJLRRb","be_java_docs_8.annotation.md":"B0qSaVqj","be_java_docs_9.maven.md":"BWB_8l9W","be_java_docs_index.md":"B8XQExlw","be_java_spring_index.md":"DWEiwh9m","be_java_tomcat_index.md":"DLj05n2P","be_node_awesome_index.md":"CFMxEo6f","be_node_docs_1.assertion-testing.md":"B30vmKjq","be_node_docs_10.cmd-line-options.md":"CHuOiaJf","be_node_docs_11.console.md":"BT0ZBSW7","be_node_docs_12.corepack.md":"CpHIW1BB","be_node_docs_13.crypto.md":"CCTIa6bg","be_node_docs_14.debugger.md":"WdXp9gbl","be_node_docs_15.deprecated-apis.md":"BxNQkgev","be_node_docs_16.diagnostics-channel.md":"B3jPAdCf","be_node_docs_17.dns.md":"BEJR6Yvv","be_node_docs_18.domain.md":"f1vawdVn","be_node_docs_19.errors.md":"CL46VZqM","be_node_docs_2.asynchronous-context-tracing.md":"BUHn2X1N","be_node_docs_3.async-hooks.md":"Br4MhEc1","be_node_docs_4.buffer.md":"BFWVep-t","be_node_docs_5.addons.md":"2y-1iQzN","be_node_docs_6.addons-with-nodejs.md":"n42Qa21c","be_node_docs_7.embedder.md":"BZbpMlNQ","be_node_docs_8.child-processes.md":"Daia4Jn6","be_node_docs_9.cluster.md":"CW44GkhB","be_node_docs_index.md":"CTtIT7qE","be_node_topic_index.md":"BhcaSgdU","be_python_docs_1.setup.md":"DHjwZh-V","be_python_docs_10.database.md":"BU8LDiUb","be_python_docs_11.web-development.md":"BtHQaxOy","be_python_docs_12.testing.md":"C2WcvEbE","be_python_docs_13.performance.md":"JeKACV0B","be_python_docs_14.tools.md":"Bem4jGTi","be_python_docs_2.data-types.md":"BJbPVJBB","be_python_docs_3.syntax.md":"idWnG8M-","be_python_docs_4.functions.md":"CJqa3CFj","be_python_docs_5.oop.md":"CkF9SkV6","be_python_docs_6.modules.md":"LXg9uocx","be_python_docs_7.exceptions.md":"CYFnSp5j","be_python_docs_8.file-io.md":"DU2p6_x9","be_python_docs_9.networking.md":"CwlNoYFk","be_python_docs_index.md":"CddlKmJT","be_ssr_ssg-vue2_index.md":"CDrLq7hQ","be_ssr_ssr-vue2_index.md":"DRqr11G9","be_standard_index.md":"Du0CwzSI","cross_h5_flexible.md":"CTZrtHyt","cross_h5_index.md":"Bka7_npa","cross_h5_orientation.md":"CKC74Qil","cross_wechat-public_1.authorization.md":"CYgs1gTq","cross_wechat-public_2.share.md":"lBj6-o89","cs_advance_algorithm_index.md":"Dw5Zhqqh","cs_advance_data-structures_1.array.md":"D7ZkjU2U","cs_advance_data-structures_2.linked-list.md":"BYRgh9a1","cs_advance_data-structures_3.stack.md":"u2fs-5ws","cs_advance_data-structures_4.queue.md":"0n-yNggW","cs_advance_data-structures_5.hash-table.md":"D4XOjPZD","cs_advance_data-structures_6.tree.md":"Du8__51d","cs_advance_data-structures_7.heap.md":"mgQwm7nY","cs_advance_data-structures_8.graph.md":"B1HUEOdP","cs_advance_data-structures_index.md":"DHMpBnMF","cs_advance_design-pattern_1.creation-pattern_1-1.factory.md":"BmweLCkH","cs_advance_design-pattern_1.creation-pattern_1-2.abstract-factory.md":"yZRF9zeW","cs_advance_design-pattern_1.creation-pattern_1-3.singleton.md":"C2CU5huA","cs_advance_design-pattern_1.creation-pattern_1-4.constructor.md":"BGVazwqN","cs_advance_design-pattern_1.creation-pattern_1-5.prototype.md":"Bv0c7mYb","cs_advance_design-pattern_2.structural-pattern_2-1.adapter.md":"C6eRXhHx","cs_advance_design-pattern_2.structural-pattern_2-2-1.decorator-constructor.md":"ijWSy8Kc","cs_advance_design-pattern_2.structural-pattern_2-2-2.decorator-class.md":"C_GEm6Hu","cs_advance_design-pattern_2.structural-pattern_2-3-1.proxy-delegate.md":"DhZn400f","cs_advance_design-pattern_2.structural-pattern_2-3-2.proxy-defineproperty.md":"yKxgB8NQ","cs_advance_design-pattern_2.structural-pattern_2-3-3.proxy-es6.md":"DtZgqD54","cs_advance_design-pattern_2.structural-pattern_2-4.facade.md":"DffUN5UE","cs_advance_design-pattern_2.structural-pattern_2-5.bridge.md":"2eqiCgzp","cs_advance_design-pattern_2.structural-pattern_2-6.composite.md":"D41NVM9G","cs_advance_design-pattern_2.structural-pattern_2-7.flyweight.md":"y8VXb2fL","cs_advance_design-pattern_3.behavioral-pattern_3-1-1.observer.md":"-EReJ3sK","cs_advance_design-pattern_3.behavioral-pattern_3-1-2.observer-publish-subscribe.md":"QbepWYD8","cs_advance_design-pattern_3.behavioral-pattern_3-10.mediator.md":"DqN3VOmJ","cs_advance_design-pattern_3.behavioral-pattern_3-11.interpreter.md":"Cs13v4Gf","cs_advance_design-pattern_3.behavioral-pattern_3-2-1.iterator.md":"Cp7A2PUy","cs_advance_design-pattern_3.behavioral-pattern_3-2-2.iterator-es6.md":"BIeghHxW","cs_advance_design-pattern_3.behavioral-pattern_3-3.strategy.md":"D3_yiMXY","cs_advance_design-pattern_3.behavioral-pattern_3-4.template-method.md":"C6J0dCcf","cs_advance_design-pattern_3.behavioral-pattern_3-5.chain-of-responsibility.md":"CuPWvrRo","cs_advance_design-pattern_3.behavioral-pattern_3-6.command.md":"Dm_uexXX","cs_advance_design-pattern_3.behavioral-pattern_3-7.memento.md":"BYLiDYvU","cs_advance_design-pattern_3.behavioral-pattern_3-8.state.md":"P8AItQkm","cs_advance_design-pattern_3.behavioral-pattern_3-9.visitor.md":"eDd67FyG","cs_advance_design-pattern_index.md":"D7HzLPvg","cs_binary-file_1.start.md":"hj6l2tso","cs_binary-file_2.arraybuffer.md":"C1FyF9xB","cs_binary-file_3.arraybufferview.md":"Dl8LlOmo","cs_binary-file_4.blob.md":"1d7k8kEI","cs_binary-file_5.file.md":"BIiHoTTS","cs_binary-file_6.filereader.md":"CqjOuebu","cs_digit_1.start.md":"BDxEk7oS","cs_digit_2.float-point.md":"r7M72bLW","cs_http_communication.md":"BdioqE2F","cs_http_cookie.md":"CgG1xmzN","cs_http_cors.md":"BpDFl8Z7","cs_http_download.md":"CPCxvlNX","cs_http_formdata.md":"rsqphBY9","cs_http_security.md":"DTyGmdip","cs_http_upload.md":"BzaVI87E","cs_http_url.md":"ORSnvmZV","cs_http_xhr-fetch.md":"umq99gMf","cs_https_encryption.md":"Bic9vCEG","cs_https_setup.md":"8rE37CsJ","cs_https_tls_ssl.md":"uRopq-qJ","cs_im_sse_1.client.md":"Dc1uTOgN","cs_im_sse_2.server.md":"BQhMmF_i","cs_im_sse_3.fetch-event-source.md":"DYYWcQiH","cs_im_sse_index.md":"B5k-KFwE","cs_im_websocket_1.client.md":"7GGuT69_","cs_im_websocket_2.server.md":"Yqd-57Ge","cs_im_websocket_index.md":"D0Sj0XV_","cs_string_1.unicode.md":"CQtY8QHs","cs_string_2.utf.md":"CJDnBxLV","cs_tcp_1.start.md":"BOj74rzv","db_mongodb_1.install.md":"DVxioAS2","db_mongodb_2.launch.md":"BvDUeuw7","db_mongodb_3.database.md":"DlXWrhGd","db_mongodb_4.table.md":"D8fCoF56","db_mongodb_5.document.md":"BfBKD0sx","db_mongodb_6.operators.md":"ltremB4a","db_mongodb_index.md":"CX7LczJQ","db_mysql_1.install.md":"C8bGRmt0","db_mysql_2.login.md":"Bnhn4n7D","db_mysql_index.md":"BFIR03g2","db_oracle_index.md":"DWZFdsjT","db_redis_1.install.md":"BUq-IQPX","db_redis_2.auth.md":"BrzwmPlP","db_redis_3.config.md":"Bm4etW7t","db_redis_4.datatype.md":"CET5y88j","db_redis_index.md":"Bpj_GOUq","db_sql_1.database.md":"68ykBpBF","db_sql_10.advance.md":"dB0AEskb","db_sql_2.table.md":"BmHqUDV4","db_sql_3.base.md":"BkNuomnG","db_sql_4.constraint.md":"Cw0y7NF5","db_sql_5.aggregate.md":"DSBcPzfG","db_sql_6.insert.md":"SG2l8Sa7","db_sql_7.select.md":"CBCiLuX3","db_sql_8.update.md":"0fRxNUiV","db_sql_9.delete.md":"CXsoGJkJ","db_sql_index.md":"CftJqJ6D","deploy_ci-cd_index.md":"ufFG_o2H","deploy_docker_1.launch.md":"C2Tf5Ih_","deploy_docker_2.image.md":"BjQFwvO6","deploy_docker_3.container.md":"D3LiV6sa","deploy_docker_4.containerization.md":"QK3KLdCe","deploy_docker_5.compose.md":"Dlfo8ytz","deploy_docker_6.swarm.md":"BYCF41V-","deploy_docker_index.md":"DWCI0B9-","deploy_jenkins_index.md":"CV-CPEln","deploy_jenkins_node-version-manager.md":"5ipuERv9","deploy_linux_index.md":"C07gFyTc","deploy_nginx_1.install.md":"DqwWA2pU","deploy_nginx_2.introduce.md":"Co0DcM3K","deploy_nginx_3.separation.md":"DE-kJgDD","deploy_nginx_4.reverseproxy.md":"DicDWMmZ","deploy_nginx_5.loadbalance.md":"DqWPowKp","deploy_nginx_index.md":"DFZfTCGZ","deploy_pm2_index.md":"8fbH-5lw","deploy_shell_1.start.md":"Bx8nfg_1","deploy_shell_2.base.md":"CIqFbhiz","deploy_shell_3.advance.md":"BV8UgjWn","engineer_babel_1.start.md":"CQARZxij","engineer_babel_2.cli.md":"495Pvue5","engineer_babel_3.config-files.md":"BZDCUGxr","engineer_babel_4.plugins.md":"Dedk_goZ","engineer_babel_5.presets.md":"2U0L3KsA","engineer_babel_6.polyfill.md":"BdsQ62sK","engineer_babel_7.transform-runtime.md":"CS04ynWd","engineer_babel_8.总结.md":"BZkjosrf","engineer_babel_index.md":"BMI92y0X","engineer_commitlint_index.md":"CVK7523R","engineer_conventional-changelog_index.md":"BIzp0b_Y","engineer_eslint_1.start.md":"BXgbqPix","engineer_eslint_10.ast.md":"DMZgM4zw","engineer_eslint_2.config-files.md":"CsQqP6Xn","engineer_eslint_3.environment.md":"CRkLB90s","engineer_eslint_4.rules.md":"DjhbNk5e","engineer_eslint_5.extends.md":"BUdbUmR4","engineer_eslint_6.plugins.md":"CcPgjICE","engineer_eslint_7.overrides.md":"Cw9BKyOR","engineer_eslint_8.ignore.md":"C0nSBBI8","engineer_eslint_9.command-line.md":"C11uKEuF","engineer_git_1.start.md":"BPxXqwHm","engineer_git_2.workspace.md":"C06ROM7Z","engineer_git_3.stage.md":"CFATmgzg","engineer_git_4.local.md":"DyTydHqq","engineer_git_5.remote.md":"DDMRhWK6","engineer_git_6.instruct.md":"BQqQOm3-","engineer_git_index.md":"DCPcvyOM","engineer_gulp_1.start.md":"BfgsY6TD","engineer_gulp_2.api.md":"D1-gMRs1","engineer_gulp_3.glob.md":"B6fOR2Yw","engineer_gulp_4.task.md":"B86j8No_","engineer_gulp_5.async.md":"CcT-hqeu","engineer_gulp_6.resources.md":"DbOB2pGQ","engineer_gulp_7.assist-tool.md":"BqGYLY7u","engineer_husky_index.md":"Cut8gYuJ","engineer_misc_obfuscator_index.md":"TQA9j5qc","engineer_mono-repo_lerna_1.start.md":"CmGBicX7","engineer_mono-repo_workspace_1.start.md":"DJhJ0GV_","engineer_mono-repo_workspace_2.npm.md":"jZFRyyKQ","engineer_mono-repo_workspace_3.yarn.md":"BhFwEXIV","engineer_mono-repo_workspace_4.pnpm.md":"AfET3v3K","engineer_pkg-manager_npm_1.start.md":"CAX1noXr","engineer_pkg-manager_npm_2.npm-cli.md":"CpQfvKOY","engineer_pkg-manager_npm_3.npm-hooks.md":"DJpG2z8-","engineer_pkg-manager_npm_4.package-json.md":"LSlj4q3z","engineer_pkg-manager_npm_5.package-lock-json.md":"QB5l_Wk5","engineer_pkg-manager_npm_6.private-registry.md":"CeCiLE47","engineer_pkg-manager_pnpm_1.start.md":"DS7Hnljp","engineer_pkg-manager_pnpm_2.motivation.md":"DirUAYC_","engineer_pkg-manager_pnpm_3.monorepo.md":"DgPjRL3C","engineer_pkg-manager_pnpm_4.publish.md":"JcU7Qs-T","engineer_pkg-manager_yarn_1.start.md":"Bzfr5RnD","engineer_postcss_1.start.md":"UIFufkfw","engineer_postcss_2.cli.md":"BkZt_0qg","engineer_postcss_3.load-config.md":"BysAELl-","engineer_postcss_4.postcss.md":"BpsxinZe","engineer_postcss_5.plugins.md":"BC0dL4hL","engineer_postcss_6.third-plugins.md":"Ce129oAs","engineer_prettier_1.start.md":"Cp5Alkrr","engineer_prettier_2.cli.md":"Bo98WczS","engineer_prettier_3.config.md":"BNBjxBlG","engineer_prettier_4.ignore.md":"mdVVfdO3","engineer_prettier_5.integrate.md":"Cu9-RKo3","engineer_prettier_ps.editorconfig.md":"CLnGsGRS","engineer_rollup_1.introduction.md":"v0qAZzyf","engineer_rollup_2.getting-started.md":"Bl5Vjkkl","engineer_rollup_3.command-line.md":"LCL1P_MX","engineer_rollup_4.config-file.md":"BNU34s3P","engineer_rollup_5.bundler.md":"DFCMSI7T","engineer_standard-version_index.md":"DpK6BdiY","engineer_ts_1.start.md":"B1bnQ4wY","engineer_ts_2.base.md":"Dp0-qMN8","engineer_ts_3.types.md":"hf3x4oX0","engineer_ts_4.array.md":"KP-uAxgs","engineer_ts_5.function.md":"b7QxFe8c","engineer_vite_1.cli.md":"YCv879HJ","engineer_vite_2.plugins.01.md":"Bu5xqG0g","engineer_vite_2.plugins.02.md":"B-MJJPie","engineer_vite_3.pre_bundling.md":"C2k6GnWp","engineer_vite_4.build.md":"DMSBJVMa","engineer_vite_5.mode.md":"B5ReQssO","engineer_vite_6.ssr.md":"zHHgu1cI","engineer_vite_7.integration.md":"X-SC_R0p","engineer_vite_8.hmr.md":"Bq7S9sgh","engineer_vite_index.md":"NMO1eIe8","engineer_webpack_1.start.md":"Dac0bars","engineer_webpack_10.devtool.md":"XUCc1FVu","engineer_webpack_11.webpack-chain.md":"ARPtG-9o","engineer_webpack_2.entry.md":"B0C-m5IG","engineer_webpack_3.output.md":"C72JZPtg","engineer_webpack_4.resolve.md":"Dw6hN_OG","engineer_webpack_5.module.md":"B1nU0h4S","engineer_webpack_6.plugins.md":"uc5AViRe","engineer_webpack_7.devserver.md":"C5ril0LU","engineer_webpack_8.environment.md":"B1EoBTyM","engineer_webpack_9.optimization.md":"K_9przy4","fe_css3_1.start.md":"BGMU1pL6","fe_css3_10.transform.md":"D1h1VZDv","fe_css3_11.animation.md":"DaQXY3vG","fe_css3_12.flex.md":"MXAp96gA","fe_css3_13.media-query.md":"Bd1rWXFz","fe_css3_2.box-sizing.md":"CVrDmfWL","fe_css3_3.border.md":"CSm7iFNW","fe_css3_4.background.md":"BmEgj_gT","fe_css3_5.gradients.md":"ByWjyQNn","fe_css3_6.shadow.md":"3wOa4mjx","fe_css3_7.text-overflow.md":"Bu4DWe6_","fe_css3_8.filter-css.md":"Ba9MOVei","fe_css3_9.transition.md":"DAJ50XPe","fe_html5_1.semantic.md":"CVUD-mc-","fe_html5_2.connectivity.md":"BpUumFVI","fe_html5_3.storage.md":"B3NgHIg7","fe_html5_4.media.md":"BYMLEwVT","fe_html5_5.graphic.md":"D8cMNbdg","fe_html5_6.integration.md":"BwJF0C_t","fe_html5_7.device.md":"Bz03Hnaz","fe_html5_8.design.md":"CARdlZn2","fe_html5_html-email.md":"Dg0LYJLD","fe_html5_index.md":"DAiriqi4","fe_html_1.attr-global.md":"CWZDGPwH","fe_html_2.attr-part.md":"Bohd2eEW","fe_html_3.attr-character.md":"hBtGnM24","fe_html_4.event.md":"BD-asfkX","fe_html_index.md":"LcwuJZCI","fe_index.md":"Cr-od083","fe_javascript_bom_1.start.md":"BaaGGBYx","fe_javascript_bom_2.screen.md":"BoXoIe7c","fe_javascript_bom_3.navigator.md":"DuWmnRZe","fe_javascript_bom_4.location.md":"B_P53h-n","fe_javascript_bom_5.history.md":"DNkpECFB","fe_javascript_dom_1.start.md":"DQgu1S6U","fe_javascript_dom_2.offset.md":"D3FBnoLq","fe_javascript_dom_3.scroll.md":"8djrQakg","fe_javascript_ecmascript_1.start.md":"B9cxR7pr","fe_javascript_ecmascript_10.object.md":"Dtaa5qEb","fe_javascript_ecmascript_3.prototype.md":"Bt5dP92k","fe_javascript_ecmascript_4.extends.md":"DcNxReeY","fe_javascript_ecmascript_7.string.md":"98dE-W_a","fe_javascript_ecmascript_8.number.md":"CU5fWnGh","fe_javascript_ecmascript_9.array.md":"D3WsB_qy","fe_javascript_index.md":"CnAUAe8Y","fe_js-advance_es6_0.start.md":"DtvP1obC","fe_js-advance_es6_1.declare.md":"Bx_zgQJa","fe_js-advance_es6_10.array.md":"U_GA0xwk","fe_js-advance_es6_11.promise.md":"B3qqLHr9","fe_js-advance_es6_12.proxy.md":"CA6axcac","fe_js-advance_es6_13.module.md":"BL41jnHv","fe_js-advance_es6_2.string.md":"CHnSWs8S","fe_js-advance_es6_3.function.md":"CQGBB1Te","fe_js-advance_es6_4.object.md":"XRdq06E9","fe_js-advance_es6_5.destruction.md":"DX6HNQZ0","fe_js-advance_es6_6.symbol.md":"DO5VH6dc","fe_js-advance_es6_7.setandmap.md":"DnyvlQjk","fe_js-advance_es6_8.iterator.md":"DL9qk-nT","fe_js-advance_es6_9.constructor-class.md":"By7dK7AU","fe_js-advance_module_1.start.md":"DpJAmyC0","fe_js-advance_module_2.iife.md":"TuEJrts6","fe_js-advance_module_3.commonjs.md":"BHqrRyCs","fe_js-advance_module_4.amd.md":"BhHVqOxb","fe_js-advance_module_5.cmd.md":"CmkRceoh","fe_js-advance_module_6.umd.md":"DD4vm6KZ","fe_js-advance_module_7.esmodule.md":"DHgzgbYP","fe_pwa_1.manifest.md":"DVlxKFwv","fe_pwa_2.serviceworker.md":"C9HmixYV","fe_pwa_3.workbox.md":"H_waI3fx","fe_pwa_4.compile.md":"CtxRHFQ4","fe_pwa_5.prompt-install.md":"C8bl_C0d","fe_pwa_6.sentry.md":"BIu060AA","fe_pwa_index.md":"BI2xxUk5","fe_rendering_1.start.md":"DHZOvpYU","fe_rendering_2.csr.md":"CJCxWwzo","fe_rendering_3.ssg.md":"Dj0UwKVN","fe_rendering_4.ssr.md":"DWPUoJbY","fe_rendering_5.isr.md":"9v10lfZs","fe_rendering_6.hr.md":"C7Pzw3rT","fe_rendering_7.esr.md":"B8BqaLlt","fe_rendering_8.swsr.md":"BgWCLvJd","fe_worker_1.webworker.md":"BW-mko-0","fe_worker_2.workerglobalscope.md":"FNW__Fc5","fe_worker_3.worker.md":"ij2tHI5k","fe_worker_4.sharedworker.md":"PINBJJqw","fe_worker_5.serviceworker.md":"Bs9UDwdv","frame_axios_base_1.install.md":"BCXrTcvA","frame_axios_base_2.config.md":"BrWlukxZ","frame_axios_base_3.alias.md":"ByFV3sLE","frame_axios_base_4.defaults.md":"HjohIj23","frame_axios_base_5.instance.md":"CA0Z6MJA","frame_axios_base_6.interceptors.md":"B21gaC9v","frame_axios_base_7.response.md":"Bby2k2SO","frame_axios_base_8.adapter.md":"SI721oYn","frame_axios_base_9.misc.md":"CQv6jdU6","frame_axios_source-code_1.start.md":"Cu9sKE1S","frame_axios_source-code_2.axios-class.md":"Bzf69-8h","frame_axios_source-code_3.interceptor.md":"D4JzUey2","frame_axios_source-code_4.dispatch-request.md":"CqilCEvM","frame_axios_source-code_5.adapter.md":"D_tX1SIC","frame_axios_source-code_6.cancel.md":"Dz3CPfMO","frame_crypto-js_base_1.start.md":"Bl0GJLS3","frame_crypto-js_base_2.hashing.md":"Cnm4IvXc","frame_crypto-js_base_3.hmac.md":"CNa3RJBz","frame_crypto-js_base_4.pbkdf2.md":"Cj1-TUlC","frame_crypto-js_base_5.ciphers.md":"YWMHhqLK","frame_crypto-js_base_6.encoders.md":"BWPgp_hC","frame_express_base_1.start.md":"Dmkd_ppV","frame_express_source-code_1.start.md":"v7BN1AyP","frame_express_source-code_2.middleware.md":"x3K-7NTj","frame_koa_base_1.start.md":"D4qlthh1","frame_koa_source-code_1.start.md":"DlHs7Dl9","frame_koa_source-code_2.middleware.md":"PvnC2Q-a","frame_nuxt_base_1.start.md":"G_LNX0K6","frame_nuxt_source-code_1.start.md":"TfcYsPy9","frame_snippets_index.md":"De-Mr4ff","frame_vue2_base_1.start.md":"BqYGeigm","frame_vue2_base_10.render.md":"D9E_ZZS1","frame_vue2_base_11.mixins.md":"C2YG5qqK","frame_vue2_base_12.keep-alive.md":"CoKVjPRN","frame_vue2_base_13.animation.md":"lu7GvqPn","frame_vue2_base_14.boundary.md":"Cc7Uu1rK","frame_vue2_base_15.plugin.md":"CnUSJdb9","frame_vue2_base_16.extend.md":"BT-SOj_H","frame_vue2_base_2.instance.md":"Drz2bUXu","frame_vue2_base_3.life-circle.md":"uLtJyMfP","frame_vue2_base_4.directives.md":"CzvmozER","frame_vue2_base_5.modifiers.md":"B3UOK17X","frame_vue2_base_6.filters.md":"BsG5hrRO","frame_vue2_base_7.computed.md":"BmGv2gEn","frame_vue2_base_8.watch.md":"Bz2N7nzw","frame_vue2_base_9.component.md":"BF5Nnd1k","frame_vue2_source-code_compiler_1.parse.md":"driin4ca","frame_vue2_source-code_compiler_2.optimize.md":"DmNMKUgh","frame_vue2_source-code_compiler_3.codegen.md":"DA1HMgEl","frame_vue2_source-code_compiler_4.to-function.md":"Dk5ituDc","frame_vue2_source-code_compiler_create-compiler.md":"Br9Et9Gf","frame_vue2_source-code_compiler_index.md":"C6yLveYJ","frame_vue2_source-code_core_global-api_index.md":"Boo9ui-0","frame_vue2_source-code_core_global-api_merge-options.md":"D8E2f8_L","frame_vue2_source-code_core_instance_events.md":"CYNYunJ-","frame_vue2_source-code_core_instance_index.md":"uwa4rsPd","frame_vue2_source-code_core_instance_inject.md":"CyojHJNe","frame_vue2_source-code_core_instance_render-helpers.md":"Du7zYJjW","frame_vue2_source-code_core_observer_1-1.observer.md":"BZV2vXAf","frame_vue2_source-code_core_observer_1-2.array.md":"B1MSaILg","frame_vue2_source-code_core_observer_2-1.dep.md":"Bi-svSef","frame_vue2_source-code_core_observer_3-1.watcher.md":"BDCzI7Qd","frame_vue2_source-code_core_observer_3-2.traverse.md":"C4ep3-3v","frame_vue2_source-code_core_observer_3-3.scheduler.md":"UpvfZJA_","frame_vue2_source-code_core_observer_index.md":"BhdmPB7P","frame_vue2_source-code_core_vdom_1.vnode.md":"1J1PkB78","frame_vue2_source-code_core_vdom_2.create-component.md":"DYlCgo1G","frame_vue2_source-code_core_vdom_3.create-element.md":"lspPYS_E","frame_vue2_source-code_core_vdom_4.create-functional-component.md":"Bsc-8QU_","frame_vue2_source-code_core_vdom_5.patch.md":"DY4IM5xA","frame_vue2_source-code_core_vdom_index.md":"BWG3owu_","frame_vue2_v3_reactivity_index.md":"CER6dqET","frame_vue2_v3_reactivity_ref_reactive.md":"C8QhGbdf","index.md":"C6Vqvj36","tool_ai_chat-gpt.md":"DL9RjuXM","tool_ai_codegpt.md":"BwKhU-Tm","tool_ai_copilot.md":"BHtvfxl0","tool_ai_index.md":"CookztjB","tool_charles_1.pc.md":"Br72rBQw","tool_charles_2.mobile.md":"CKCRDCTd","tool_charles_index.md":"CN5Hp2ua","tool_chrome_index.md":"ChBiLMgL","tool_chrome_memory.md":"07spCFPt","tool_chrome_performance.md":"DCCnECyj","tool_github_actions.md":"6id80iNv","tool_github_index.md":"D5uVpws8","tool_issue_cant-find-python-executable.md":"DyyKiNeL","tool_localtunnel_index.md":"XEc1loME","tool_remote-ssh_index.md":"Dj2NYZnD","tool_verdaccio_index.md":"3zEddYvt","tool_vitepress_index.md":"CflXpCjX"}
